setup.py
SimpleFlask.egg-info/PKG-INFO
SimpleFlask.egg-info/SOURCES.txt
SimpleFlask.egg-info/dependency_links.txt
SimpleFlask.egg-info/requires.txt
SimpleFlask.egg-info/top_level.txt
simple_flask/__init__.py
simple_flask/core/__init__.py
simple_flask/core/core.py
simple_flask/rest/__init__.py
simple_flask/rest/rest.py