Metadata-Version: 1.0
Name: SimpleFlask
Version: 0.1.0
Summary: Simple Flask application.
Home-page: http://pypi.python.org/pypi/SimpleFlask/
Author: Guido Barbaglia
Author-email: guido.barbaglia@gmail.com
License: LICENSE.txt
Platform: UNKNOWN
